{
  "name": "mmPackage",
  "type": "package",
  "source": {
    "https": "https://github.com/Digambaran/mmPackage.git",
    "ssh": "git@github.com:Digambaran/mmPackage.git",
    "branch": "block_mmPackage"
  },
  "dependencies": {
    "removeTodo": {
      "directory": "removeTodo"
    },
    "addTodo": {
      "directory": "addTodo"
    },
    "listTodos": {
      "directory": "listTodos"
    },
    "todoItem": {
      "directory": "todoItem"
    },
    "todoInput": {
      "directory": "todoInput"
    },
    "todoContainer": {
      "directory": "todoContainer"
    }
  },
  "blockId": "O8LxLDA0yw12kEE5h8exf",
  "parentBlockIDs": [],
  "isPublic": true,
  "supportedAppblockVersions": [
    "1.0.0"
  ],
  "repoType": "mono"
}